ma_notification_center/__init__.py
ma_notification_center/notificationcenter.py
ma_notification_center-2.1.1.dist-info/LICENSE
ma_notification_center-2.1.1.dist-info/METADATA
ma_notification_center-2.1.1.dist-info/WHEEL
ma_notification_center-2.1.1.dist-info/top_level.txt
ma_notification_center-2.1.1.dist-info/RECORD
