Metadata-Version: 2.1
Name: ma-notification-center
Version: 2.1.1
Summary: MobileArts Notification Center Package
Author: Fatima Medlij
Author-email: medlijfatima@gmail.com
License: MIT
License-File: LICENSE
Requires-Dist: boto3
Requires-Dist: email-validator
